fastcookie/__init__.py
fastcookie-0.0.2.dist-info/LICENSE
fastcookie-0.0.2.dist-info/METADATA
fastcookie-0.0.2.dist-info/WHEEL
fastcookie-0.0.2.dist-info/top_level.txt
fastcookie-0.0.2.dist-info/RECORD
