Metadata-Version: 2.1
Name: fastcookie
Version: 0.0.2
Summary: make it easy to use cookie
Home-page: https://gitee.com/ZeroSeeker/fastcookie
Author: ZeroSeeker
Author-email: zeroseeker@foxmail.com
Classifier: Programming Language :: Python :: 3
Classifier: License :: OSI Approved :: MIT License
Classifier: Operating System :: OS Independent
License-File: LICENSE
Requires-Dist: requests >=2.27.1
